odoo/addons/contract_group/__init__.py
odoo/addons/contract_group/__manifest__.py
odoo/addons/contract_group/models/__init__.py
odoo/addons/contract_group/models/account_invoice.py
odoo/addons/contract_group/models/account_move.py
odoo/addons/contract_group/models/contract_contract.py
odoo/addons/contract_group/models/contract_group.py
odoo/addons/contract_group/models/__pycache__/__init__.cpython-37.pyc
odoo/addons/contract_group/models/__pycache__/account_invoice.cpython-37.pyc
odoo/addons/contract_group/models/__pycache__/contract_contract.cpython-37.pyc
odoo/addons/contract_group/models/__pycache__/contract_group.cpython-37.pyc
odoo/addons/contract_group/security/ir.model.access.csv
odoo/addons/contract_group/views/account_invoice.xml
odoo/addons/contract_group/views/account_move.xml
odoo/addons/contract_group/views/contract_contract.xml
odoo/addons/contract_group/views/contract_group.xml
odoo_addon_contract_group-16.0.0.0.1.1.dist-info/METADATA
odoo_addon_contract_group-16.0.0.0.1.1.dist-info/WHEEL
odoo_addon_contract_group-16.0.0.0.1.1.dist-info/top_level.txt
odoo_addon_contract_group-16.0.0.0.1.1.dist-info/RECORD
